setup.cfg
setup.py
simulatesv/__init__.py
simulatesv/simulatesv.py
simulatesv.egg-info/PKG-INFO
simulatesv.egg-info/SOURCES.txt
simulatesv.egg-info/dependency_links.txt
simulatesv.egg-info/requires.txt
simulatesv.egg-info/top_level.txt
test/test_simulatesv.py