Metadata-Version: 1.1
Name: simulatesv
Version: 0.2.0
Summary: Simulate structural variations and SNPs with artificial dna sequences
Home-page: https://github.com/mlliou112/simulatesv
Author: Michael Liou
Author-email: mliou112@yahoo.com
License: MIT
Keywords: bioinformatics structural-variation simulate dna genetics sequencing
Platform: UNKNOWN
Classifier: Development Status :: 4 - Beta
Classifier: Intended Audience :: Science/Research
Classifier: License :: OSI Approved :: MIT License
Classifier: Programming Language :: Python :: 2.7
Classifier: Programming Language :: Python :: 3.2
Classifier: Programming Language :: Python :: 3.3
Classifier: Programming Language :: Python :: 3.4
Classifier: Programming Language :: Python :: 3.5
Classifier: Programming Language :: Python :: 3.6
Classifier: Topic :: Scientific/Engineering :: Bio-Informatics
